airpage/__init__.py
airpage/cmd_entry.py
airpage/core/__init__.py
airpage/core/_basic.py
airpage/core/_btree.py
airpage/core/_ocr.py
airpage/core/ap_leafs.py
airpage/core/core.py
airpage/core/page.py
airpage-0.1.4.dist-info/METADATA
airpage-0.1.4.dist-info/WHEEL
airpage-0.1.4.dist-info/entry_points.txt
airpage-0.1.4.dist-info/top_level.txt
airpage-0.1.4.dist-info/RECORD
