Metadata-Version: 2.1
Name: airpage
Version: 0.1.4
Summary: based on airtest
Home-page: https://gitee.com/eagle-s_baby/airpage
Author: eaglebaby
Author-email: 2229066748@qq.com
Platform: Windows
Classifier: Development Status :: 3 - Alpha
Classifier: License :: OSI Approved :: GNU General Public License (GPL)
Requires-Python: ==3.9.*
Requires-Dist: py-trees
Requires-Dist: airtest
Requires-Dist: pyautogui
Requires-Dist: files3
Requires-Dist: pywin32
Requires-Dist: pydotplus
Requires-Dist: wxauto
